{
  "_meta": {
    "schema_version": "1.0.0-draft",
    "status": "draft_reviewed",
    "generated_at": "2026-06-02T20:52:38Z",
    "scope_id": "grade7_coding_and_robotics_en",
    "scope": "Grade 7 Coding and Robotics",
    "suggested_runtime_topic_map_path": "data/caps/topic_maps/grade7_coding_and_robotics_en.json",
    "source_document_ids": [
      "caps_senior_coding_and_robotics_en"
    ],
    "source_paths": [
      "data/caps/source_documents/raw/caps_senior_coding_and_robotics_en.pdf"
    ],
    "source_sha256": [
      "04ae21e3899fa9df3c52c243c0b5d876fccadd89c8af63ab66d02d40c5ac6036"
    ],
    "canonical_source_urls": [
      "https://www.education.gov.za/LinkClick.aspx?fileticket=1M7krZtYs24%3d&tabid=573&portalid=0&mid=13088&forcedownload=true"
    ],
    "object_store_uris": [
      "https://eduboostcaps06022047.blob.core.windows.net/caps-sources/senior/coding-and-robotics/en/caps_senior_coding_and_robotics_en-04ae21e3899fa9df.pdf"
    ],
    "text_extract_paths": [
      "data/caps/source_documents/text/caps_senior_coding_and_robotics_en.txt"
    ],
    "text_sha256": [
      "efedbdecb16a8e94a05b24baed59741095017e8125fe42ebdab3d4035b84c36c"
    ],
    "outstanding_tasks": [
      "generate_reviewed_content",
      "activate_scope_for_learners"
    ],
    "review_required": false,
    "notes": "Reviewed topic map populated for generation planning; learner visibility remains gated by active scope status and strict content validation.",
    "reviewed_at": "2026-06-03T00:00:00Z",
    "reviewer_id": "curriculum-population-batch-2026-06-03"
  },
  "grade": 7,
  "subject": "Coding and Robotics",
  "subject_code": "CR",
  "terms": [
    {
      "term": 1,
      "weeks": "1-10",
      "topics": [
        {
          "caps_ref": "7.CR.1.1",
          "topic_index": 1,
          "topic": "Pattern recognition and decomposition",
          "subtopics": [
            {
              "caps_ref": "7.CR.1.1.1",
              "subtopic_index": 1,
              "subtopic": "Pattern recognition and decomposition",
              "assessment_standards": [
                "Apply the design/problem-solving process to pattern recognition and decomposition.",
                "Build, test, debug or evaluate a solution using appropriate tools and terminology.",
                "Communicate decisions, results and improvements clearly."
              ],
              "prerequisites": [],
              "common_misconceptions": [
                "topic_vocabulary_confusion",
                "procedure_without_conceptual_understanding"
              ]
            }
          ]
        },
        {
          "caps_ref": "7.CR.1.2",
          "topic_index": 2,
          "topic": "Algorithms and coding",
          "subtopics": [
            {
              "caps_ref": "7.CR.1.2.1",
              "subtopic_index": 1,
              "subtopic": "Algorithms and coding",
              "assessment_standards": [
                "Apply the design/problem-solving process to algorithms and coding.",
                "Build, test, debug or evaluate a solution using appropriate tools and terminology.",
                "Communicate decisions, results and improvements clearly."
              ],
              "prerequisites": [
                "7.CR.1.1"
              ],
              "common_misconceptions": [
                "topic_vocabulary_confusion",
                "procedure_without_conceptual_understanding"
              ]
            }
          ]
        },
        {
          "caps_ref": "7.CR.1.3",
          "topic_index": 3,
          "topic": "Robotics and mechanical systems",
          "subtopics": [
            {
              "caps_ref": "7.CR.1.3.1",
              "subtopic_index": 1,
              "subtopic": "Robotics and mechanical systems",
              "assessment_standards": [
                "Apply the design/problem-solving process to robotics and mechanical systems.",
                "Build, test, debug or evaluate a solution using appropriate tools and terminology.",
                "Communicate decisions, results and improvements clearly."
              ],
              "prerequisites": [
                "7.CR.1.1"
              ],
              "common_misconceptions": [
                "topic_vocabulary_confusion",
                "procedure_without_conceptual_understanding"
              ]
            }
          ]
        },
        {
          "caps_ref": "7.CR.1.4",
          "topic_index": 4,
          "topic": "Digital concepts",
          "subtopics": [
            {
              "caps_ref": "7.CR.1.4.1",
              "subtopic_index": 1,
              "subtopic": "Digital concepts",
              "assessment_standards": [
                "Apply the design/problem-solving process to digital concepts.",
                "Build, test, debug or evaluate a solution using appropriate tools and terminology.",
                "Communicate decisions, results and improvements clearly."
              ],
              "prerequisites": [
                "7.CR.1.1"
              ],
              "common_misconceptions": [
                "topic_vocabulary_confusion",
                "procedure_without_conceptual_understanding"
              ]
            }
          ]
        }
      ]
    },
    {
      "term": 2,
      "weeks": "1-10",
      "topics": [
        {
          "caps_ref": "7.CR.2.1",
          "topic_index": 1,
          "topic": "Algorithms and coding",
          "subtopics": [
            {
              "caps_ref": "7.CR.2.1.1",
              "subtopic_index": 1,
              "subtopic": "Algorithms and coding",
              "assessment_standards": [
                "Apply the design/problem-solving process to algorithms and coding.",
                "Build, test, debug or evaluate a solution using appropriate tools and terminology.",
                "Communicate decisions, results and improvements clearly."
              ],
              "prerequisites": [
                "7.CR.1.1"
              ],
              "common_misconceptions": [
                "topic_vocabulary_confusion",
                "procedure_without_conceptual_understanding"
              ]
            }
          ]
        },
        {
          "caps_ref": "7.CR.2.2",
          "topic_index": 2,
          "topic": "Robotics and sensors",
          "subtopics": [
            {
              "caps_ref": "7.CR.2.2.1",
              "subtopic_index": 1,
              "subtopic": "Robotics and sensors",
              "assessment_standards": [
                "Apply the design/problem-solving process to robotics and sensors.",
                "Build, test, debug or evaluate a solution using appropriate tools and terminology.",
                "Communicate decisions, results and improvements clearly."
              ],
              "prerequisites": [
                "7.CR.1.1"
              ],
              "common_misconceptions": [
                "topic_vocabulary_confusion",
                "procedure_without_conceptual_understanding"
              ]
            }
          ]
        },
        {
          "caps_ref": "7.CR.2.3",
          "topic_index": 3,
          "topic": "Data and digital systems",
          "subtopics": [
            {
              "caps_ref": "7.CR.2.3.1",
              "subtopic_index": 1,
              "subtopic": "Data and digital systems",
              "assessment_standards": [
                "Apply the design/problem-solving process to data and digital systems.",
                "Build, test, debug or evaluate a solution using appropriate tools and terminology.",
                "Communicate decisions, results and improvements clearly."
              ],
              "prerequisites": [
                "7.CR.1.1"
              ],
              "common_misconceptions": [
                "topic_vocabulary_confusion",
                "procedure_without_conceptual_understanding"
              ]
            }
          ]
        },
        {
          "caps_ref": "7.CR.2.4",
          "topic_index": 4,
          "topic": "Problem solving",
          "subtopics": [
            {
              "caps_ref": "7.CR.2.4.1",
              "subtopic_index": 1,
              "subtopic": "Problem solving",
              "assessment_standards": [
                "Apply the design/problem-solving process to problem solving.",
                "Build, test, debug or evaluate a solution using appropriate tools and terminology.",
                "Communicate decisions, results and improvements clearly."
              ],
              "prerequisites": [
                "7.CR.1.1"
              ],
              "common_misconceptions": [
                "topic_vocabulary_confusion",
                "procedure_without_conceptual_understanding"
              ]
            }
          ]
        }
      ]
    },
    {
      "term": 3,
      "weeks": "1-10",
      "topics": [
        {
          "caps_ref": "7.CR.3.1",
          "topic_index": 1,
          "topic": "Coding projects",
          "subtopics": [
            {
              "caps_ref": "7.CR.3.1.1",
              "subtopic_index": 1,
              "subtopic": "Coding projects",
              "assessment_standards": [
                "Apply the design/problem-solving process to coding projects.",
                "Build, test, debug or evaluate a solution using appropriate tools and terminology.",
                "Communicate decisions, results and improvements clearly."
              ],
              "prerequisites": [
                "7.CR.2.1"
              ],
              "common_misconceptions": [
                "topic_vocabulary_confusion",
                "procedure_without_conceptual_understanding"
              ]
            }
          ]
        },
        {
          "caps_ref": "7.CR.3.2",
          "topic_index": 2,
          "topic": "Robotics projects",
          "subtopics": [
            {
              "caps_ref": "7.CR.3.2.1",
              "subtopic_index": 1,
              "subtopic": "Robotics projects",
              "assessment_standards": [
                "Apply the design/problem-solving process to robotics projects.",
                "Build, test, debug or evaluate a solution using appropriate tools and terminology.",
                "Communicate decisions, results and improvements clearly."
              ],
              "prerequisites": [
                "7.CR.2.1"
              ],
              "common_misconceptions": [
                "topic_vocabulary_confusion",
                "procedure_without_conceptual_understanding"
              ]
            }
          ]
        },
        {
          "caps_ref": "7.CR.3.3",
          "topic_index": 3,
          "topic": "Internet and digital citizenship",
          "subtopics": [
            {
              "caps_ref": "7.CR.3.3.1",
              "subtopic_index": 1,
              "subtopic": "Internet and digital citizenship",
              "assessment_standards": [
                "Apply the design/problem-solving process to internet and digital citizenship.",
                "Build, test, debug or evaluate a solution using appropriate tools and terminology.",
                "Communicate decisions, results and improvements clearly."
              ],
              "prerequisites": [
                "7.CR.2.1"
              ],
              "common_misconceptions": [
                "topic_vocabulary_confusion",
                "procedure_without_conceptual_understanding"
              ]
            }
          ]
        },
        {
          "caps_ref": "7.CR.3.4",
          "topic_index": 4,
          "topic": "Integrated design challenge",
          "subtopics": [
            {
              "caps_ref": "7.CR.3.4.1",
              "subtopic_index": 1,
              "subtopic": "Integrated design challenge",
              "assessment_standards": [
                "Apply the design/problem-solving process to integrated design challenge.",
                "Build, test, debug or evaluate a solution using appropriate tools and terminology.",
                "Communicate decisions, results and improvements clearly."
              ],
              "prerequisites": [
                "7.CR.2.1"
              ],
              "common_misconceptions": [
                "topic_vocabulary_confusion",
                "procedure_without_conceptual_understanding"
              ]
            }
          ]
        }
      ]
    },
    {
      "term": 4,
      "weeks": "1-8",
      "topics": [
        {
          "caps_ref": "7.CR.4.1",
          "topic_index": 1,
          "topic": "Consolidation, debugging and assessment",
          "subtopics": [
            {
              "caps_ref": "7.CR.4.1.1",
              "subtopic_index": 1,
              "subtopic": "Consolidation, debugging and assessment",
              "assessment_standards": [
                "Apply the design/problem-solving process to consolidation, debugging and assessment.",
                "Build, test, debug or evaluate a solution using appropriate tools and terminology.",
                "Communicate decisions, results and improvements clearly."
              ],
              "prerequisites": [
                "7.CR.3.1"
              ],
              "common_misconceptions": [
                "topic_vocabulary_confusion",
                "procedure_without_conceptual_understanding"
              ]
            }
          ]
        },
        {
          "caps_ref": "7.CR.4.2",
          "topic_index": 2,
          "topic": "Robotics control",
          "subtopics": [
            {
              "caps_ref": "7.CR.4.2.1",
              "subtopic_index": 1,
              "subtopic": "Robotics control",
              "assessment_standards": [
                "Apply the design/problem-solving process to robotics control.",
                "Build, test, debug or evaluate a solution using appropriate tools and terminology.",
                "Communicate decisions, results and improvements clearly."
              ],
              "prerequisites": [
                "7.CR.3.1"
              ],
              "common_misconceptions": [
                "topic_vocabulary_confusion",
                "procedure_without_conceptual_understanding"
              ]
            }
          ]
        },
        {
          "caps_ref": "7.CR.4.3",
          "topic_index": 3,
          "topic": "Data representation",
          "subtopics": [
            {
              "caps_ref": "7.CR.4.3.1",
              "subtopic_index": 1,
              "subtopic": "Data representation",
              "assessment_standards": [
                "Apply the design/problem-solving process to data representation.",
                "Build, test, debug or evaluate a solution using appropriate tools and terminology.",
                "Communicate decisions, results and improvements clearly."
              ],
              "prerequisites": [
                "7.CR.3.1"
              ],
              "common_misconceptions": [
                "topic_vocabulary_confusion",
                "procedure_without_conceptual_understanding"
              ]
            }
          ]
        },
        {
          "caps_ref": "7.CR.4.4",
          "topic_index": 4,
          "topic": "Integrated project",
          "subtopics": [
            {
              "caps_ref": "7.CR.4.4.1",
              "subtopic_index": 1,
              "subtopic": "Integrated project",
              "assessment_standards": [
                "Apply the design/problem-solving process to integrated project.",
                "Build, test, debug or evaluate a solution using appropriate tools and terminology.",
                "Communicate decisions, results and improvements clearly."
              ],
              "prerequisites": [
                "7.CR.3.1"
              ],
              "common_misconceptions": [
                "topic_vocabulary_confusion",
                "procedure_without_conceptual_understanding"
              ]
            }
          ]
        }
      ]
    }
  ]
}
