{
  "schema_version": "1.0",
  "generated_at": "2026-06-03T19:40:23Z",
  "scope": "grade6_home_language_en",
  "grade": 6,
  "subject": "Home Language",
  "weekly_template": [
    {
      "day": "Mon",
      "caps_ref": "6.HL.1.1",
      "topic": "Listening and speaking",
      "activity_type": "lesson",
      "lesson_variant": "standard",
      "assessment_blueprint_id": "grade6-home-language-en-6-HL-1-1-short-practice-v2",
      "minutes": 40,
      "teacher_cue": "Teach Listening and speaking using the worked examples, then set the short practice blueprint."
    },
    {
      "day": "Tue",
      "caps_ref": "6.HL.1.2",
      "topic": "Reading and viewing",
      "activity_type": "practice",
      "lesson_variant": "visual",
      "assessment_blueprint_id": "grade6-home-language-en-6-HL-1-2-short-practice-v2",
      "minutes": 25,
      "teacher_cue": "Run the short practice quiz for Reading and viewing and note missed misconception tags."
    },
    {
      "day": "Wed",
      "caps_ref": "6.HL.1.3",
      "topic": "Writing and presenting",
      "activity_type": "lesson",
      "lesson_variant": "story",
      "assessment_blueprint_id": "grade6-home-language-en-6-HL-1-3-short-practice-v2",
      "minutes": 40,
      "teacher_cue": "Teach Writing and presenting using the worked examples, then set the short practice blueprint."
    },
    {
      "day": "Thu",
      "caps_ref": "6.HL.1.4",
      "topic": "Language structures and conventions",
      "activity_type": "practice",
      "lesson_variant": "step_by_step",
      "assessment_blueprint_id": "grade6-home-language-en-6-HL-1-4-short-practice-v2",
      "minutes": 25,
      "teacher_cue": "Run the short practice quiz for Language structures and conventions and note missed misconception tags."
    },
    {
      "day": "Fri",
      "caps_ref": "6.HL.2.1",
      "topic": "Listening and speaking",
      "activity_type": "review",
      "lesson_variant": "real_world_sa",
      "assessment_blueprint_id": "grade6-home-language-en-6-HL-2-1-recheck-v2",
      "minutes": 25,
      "teacher_cue": "Use the recheck blueprint for Listening and speaking and assign step-by-step remediation where needed."
    }
  ],
  "topic_sequence": [
    {
      "caps_ref": "6.HL.1.1",
      "topic": "Listening and speaking",
      "subtopic": "Listening and speaking",
      "term": 1,
      "prerequisites": [],
      "misconception_tags": [
        "topic_vocabulary_confusion",
        "procedure_without_conceptual_understanding"
      ],
      "assessment_standards": [
        "Engage with listening and speaking tasks appropriate to the grade and language level.",
        "Use vocabulary, comprehension strategies and conventions from the CAPS source document."
      ],
      "source_context_hash": "sha256:74999f6758c819bb37cee05c1030e4d655685ff8d91220b43dc08f652b5eb2a6",
      "recommended_lesson_variants": [
        "standard",
        "visual",
        "story",
        "step_by_step"
      ]
    },
    {
      "caps_ref": "6.HL.1.2",
      "topic": "Reading and viewing",
      "subtopic": "Reading and viewing",
      "term": 1,
      "prerequisites": [
        "6.HL.1.1"
      ],
      "misconception_tags": [
        "topic_vocabulary_confusion",
        "procedure_without_conceptual_understanding"
      ],
      "assessment_standards": [
        "Engage with reading and viewing tasks appropriate to the grade and language level.",
        "Use vocabulary, comprehension strategies and conventions from the CAPS source document."
      ],
      "source_context_hash": "sha256:7c67bdaffc638c9e786e9dff87eecb6dc7a6e094cacea9e50509f5ceb1bf51c9",
      "recommended_lesson_variants": [
        "standard",
        "visual",
        "story",
        "step_by_step"
      ]
    },
    {
      "caps_ref": "6.HL.1.3",
      "topic": "Writing and presenting",
      "subtopic": "Writing and presenting",
      "term": 1,
      "prerequisites": [
        "6.HL.1.1"
      ],
      "misconception_tags": [
        "topic_vocabulary_confusion",
        "procedure_without_conceptual_understanding"
      ],
      "assessment_standards": [
        "Engage with writing and presenting tasks appropriate to the grade and language level.",
        "Use vocabulary, comprehension strategies and conventions from the CAPS source document."
      ],
      "source_context_hash": "sha256:146876f2dfc88ca8b2e9f80e99c4fa6df4fbc56e900354655f2233c140cf7ee3",
      "recommended_lesson_variants": [
        "standard",
        "visual",
        "story",
        "step_by_step"
      ]
    },
    {
      "caps_ref": "6.HL.1.4",
      "topic": "Language structures and conventions",
      "subtopic": "Language structures and conventions",
      "term": 1,
      "prerequisites": [
        "6.HL.1.1"
      ],
      "misconception_tags": [
        "topic_vocabulary_confusion",
        "procedure_without_conceptual_understanding"
      ],
      "assessment_standards": [
        "Engage with language structures and conventions tasks appropriate to the grade and language level.",
        "Use vocabulary, comprehension strategies and conventions from the CAPS source document."
      ],
      "source_context_hash": "sha256:6e924cbb8b71e87f1ec01ed0e132d596abc5817643541794f66ad18be1b9f62d",
      "recommended_lesson_variants": [
        "standard",
        "visual",
        "story",
        "step_by_step"
      ]
    },
    {
      "caps_ref": "6.HL.2.1",
      "topic": "Listening and speaking",
      "subtopic": "Listening and speaking",
      "term": 2,
      "prerequisites": [
        "6.HL.1.1"
      ],
      "misconception_tags": [
        "topic_vocabulary_confusion",
        "procedure_without_conceptual_understanding"
      ],
      "assessment_standards": [
        "Engage with listening and speaking tasks appropriate to the grade and language level.",
        "Use vocabulary, comprehension strategies and conventions from the CAPS source document."
      ],
      "source_context_hash": "sha256:74e02c0589964de306dfc93df2911dde10e55008cfaf7050ca1079351a6f26ab",
      "recommended_lesson_variants": [
        "standard",
        "visual",
        "story",
        "step_by_step"
      ]
    },
    {
      "caps_ref": "6.HL.2.2",
      "topic": "Reading and viewing",
      "subtopic": "Reading and viewing",
      "term": 2,
      "prerequisites": [
        "6.HL.1.1"
      ],
      "misconception_tags": [
        "topic_vocabulary_confusion",
        "procedure_without_conceptual_understanding"
      ],
      "assessment_standards": [
        "Engage with reading and viewing tasks appropriate to the grade and language level.",
        "Use vocabulary, comprehension strategies and conventions from the CAPS source document."
      ],
      "source_context_hash": "sha256:ce97bc6113a576d9dc2d620770cf4afd8accadd8b43eca892c679fad1a0afef6",
      "recommended_lesson_variants": [
        "standard",
        "visual",
        "story",
        "step_by_step"
      ]
    },
    {
      "caps_ref": "6.HL.2.3",
      "topic": "Writing and presenting",
      "subtopic": "Writing and presenting",
      "term": 2,
      "prerequisites": [
        "6.HL.1.1"
      ],
      "misconception_tags": [
        "topic_vocabulary_confusion",
        "procedure_without_conceptual_understanding"
      ],
      "assessment_standards": [
        "Engage with writing and presenting tasks appropriate to the grade and language level.",
        "Use vocabulary, comprehension strategies and conventions from the CAPS source document."
      ],
      "source_context_hash": "sha256:a9e5608957a6fa9228aa087701ff1e27db51a9c7fa84e5e1a0b219d90bb4919d",
      "recommended_lesson_variants": [
        "standard",
        "visual",
        "story",
        "step_by_step"
      ]
    },
    {
      "caps_ref": "6.HL.2.4",
      "topic": "Language structures and conventions",
      "subtopic": "Language structures and conventions",
      "term": 2,
      "prerequisites": [
        "6.HL.1.1"
      ],
      "misconception_tags": [
        "topic_vocabulary_confusion",
        "procedure_without_conceptual_understanding"
      ],
      "assessment_standards": [
        "Engage with language structures and conventions tasks appropriate to the grade and language level.",
        "Use vocabulary, comprehension strategies and conventions from the CAPS source document."
      ],
      "source_context_hash": "sha256:271993b1676d390d0b9e014798eef3f0162a6d6996ba9b2df7a08452b6064cc7",
      "recommended_lesson_variants": [
        "standard",
        "visual",
        "story",
        "step_by_step"
      ]
    },
    {
      "caps_ref": "6.HL.3.1",
      "topic": "Listening and speaking",
      "subtopic": "Listening and speaking",
      "term": 3,
      "prerequisites": [
        "6.HL.2.1"
      ],
      "misconception_tags": [
        "topic_vocabulary_confusion",
        "procedure_without_conceptual_understanding"
      ],
      "assessment_standards": [
        "Engage with listening and speaking tasks appropriate to the grade and language level.",
        "Use vocabulary, comprehension strategies and conventions from the CAPS source document."
      ],
      "source_context_hash": "sha256:52a9db690c00c5e292667764326f6afadcdaa7c1c6a0d9da13d61be840c35c79",
      "recommended_lesson_variants": [
        "standard",
        "visual",
        "story",
        "step_by_step"
      ]
    },
    {
      "caps_ref": "6.HL.3.2",
      "topic": "Reading and viewing",
      "subtopic": "Reading and viewing",
      "term": 3,
      "prerequisites": [
        "6.HL.2.1"
      ],
      "misconception_tags": [
        "topic_vocabulary_confusion",
        "procedure_without_conceptual_understanding"
      ],
      "assessment_standards": [
        "Engage with reading and viewing tasks appropriate to the grade and language level.",
        "Use vocabulary, comprehension strategies and conventions from the CAPS source document."
      ],
      "source_context_hash": "sha256:b32ea887a37063ddfe2593cb99b940127fc63cdab219b9a8bb1dee1e68c128a9",
      "recommended_lesson_variants": [
        "standard",
        "visual",
        "story",
        "step_by_step"
      ]
    },
    {
      "caps_ref": "6.HL.3.3",
      "topic": "Writing and presenting",
      "subtopic": "Writing and presenting",
      "term": 3,
      "prerequisites": [
        "6.HL.2.1"
      ],
      "misconception_tags": [
        "topic_vocabulary_confusion",
        "procedure_without_conceptual_understanding"
      ],
      "assessment_standards": [
        "Engage with writing and presenting tasks appropriate to the grade and language level.",
        "Use vocabulary, comprehension strategies and conventions from the CAPS source document."
      ],
      "source_context_hash": "sha256:cf2a80688643a5a0db2a56f49e9cc4cb9521a42298c15e72f069403cb3cef941",
      "recommended_lesson_variants": [
        "standard",
        "visual",
        "story",
        "step_by_step"
      ]
    },
    {
      "caps_ref": "6.HL.3.4",
      "topic": "Language structures and conventions",
      "subtopic": "Language structures and conventions",
      "term": 3,
      "prerequisites": [
        "6.HL.2.1"
      ],
      "misconception_tags": [
        "topic_vocabulary_confusion",
        "procedure_without_conceptual_understanding"
      ],
      "assessment_standards": [
        "Engage with language structures and conventions tasks appropriate to the grade and language level.",
        "Use vocabulary, comprehension strategies and conventions from the CAPS source document."
      ],
      "source_context_hash": "sha256:1e5b5fb117106521d242a4adfbe2d8c97e97f7306f319fad3fc7bb91f1b8cbbf",
      "recommended_lesson_variants": [
        "standard",
        "visual",
        "story",
        "step_by_step"
      ]
    },
    {
      "caps_ref": "6.HL.4.1",
      "topic": "Listening and speaking",
      "subtopic": "Listening and speaking",
      "term": 4,
      "prerequisites": [
        "6.HL.3.1"
      ],
      "misconception_tags": [
        "topic_vocabulary_confusion",
        "procedure_without_conceptual_understanding"
      ],
      "assessment_standards": [
        "Engage with listening and speaking tasks appropriate to the grade and language level.",
        "Use vocabulary, comprehension strategies and conventions from the CAPS source document."
      ],
      "source_context_hash": "sha256:1d4c9447e0102aa0d4157bba172412b9bc9456e1615ad293faa373902280f280",
      "recommended_lesson_variants": [
        "standard",
        "visual",
        "story",
        "step_by_step"
      ]
    },
    {
      "caps_ref": "6.HL.4.2",
      "topic": "Reading and viewing",
      "subtopic": "Reading and viewing",
      "term": 4,
      "prerequisites": [
        "6.HL.3.1"
      ],
      "misconception_tags": [
        "topic_vocabulary_confusion",
        "procedure_without_conceptual_understanding"
      ],
      "assessment_standards": [
        "Engage with reading and viewing tasks appropriate to the grade and language level.",
        "Use vocabulary, comprehension strategies and conventions from the CAPS source document."
      ],
      "source_context_hash": "sha256:5b79fad84f08481d75dbc1c93e8cea22091becec4e65df6cbdd081dfd7430140",
      "recommended_lesson_variants": [
        "standard",
        "visual",
        "story",
        "step_by_step"
      ]
    },
    {
      "caps_ref": "6.HL.4.3",
      "topic": "Writing and presenting",
      "subtopic": "Writing and presenting",
      "term": 4,
      "prerequisites": [
        "6.HL.3.1"
      ],
      "misconception_tags": [
        "topic_vocabulary_confusion",
        "procedure_without_conceptual_understanding"
      ],
      "assessment_standards": [
        "Engage with writing and presenting tasks appropriate to the grade and language level.",
        "Use vocabulary, comprehension strategies and conventions from the CAPS source document."
      ],
      "source_context_hash": "sha256:0140912d6ddc2030054edfa05760949238029b606acab9afbe114377f86c3185",
      "recommended_lesson_variants": [
        "standard",
        "visual",
        "story",
        "step_by_step"
      ]
    },
    {
      "caps_ref": "6.HL.4.4",
      "topic": "Language structures and conventions",
      "subtopic": "Language structures and conventions",
      "term": 4,
      "prerequisites": [
        "6.HL.3.1"
      ],
      "misconception_tags": [
        "topic_vocabulary_confusion",
        "procedure_without_conceptual_understanding"
      ],
      "assessment_standards": [
        "Engage with language structures and conventions tasks appropriate to the grade and language level.",
        "Use vocabulary, comprehension strategies and conventions from the CAPS source document."
      ],
      "source_context_hash": "sha256:7159551f055441ddcfee3ded838df6cc13e855ce5fc736776f88a5768bbb936b",
      "recommended_lesson_variants": [
        "standard",
        "visual",
        "story",
        "step_by_step"
      ]
    }
  ],
  "remediation_mappings": [
    {
      "misconception_tag": "topic_vocabulary_confusion",
      "caps_ref": "6.HL.1.1",
      "topic": "Listening and speaking",
      "lesson_variant": "step_by_step",
      "assessment_blueprint_id": "grade6-home-language-en-6-HL-1-1-recheck-v2",
      "activity_type": "remediation",
      "minutes": 20
    },
    {
      "misconception_tag": "procedure_without_conceptual_understanding",
      "caps_ref": "6.HL.1.1",
      "topic": "Listening and speaking",
      "lesson_variant": "step_by_step",
      "assessment_blueprint_id": "grade6-home-language-en-6-HL-1-1-recheck-v2",
      "activity_type": "remediation",
      "minutes": 20
    },
    {
      "misconception_tag": "topic_vocabulary_confusion",
      "caps_ref": "6.HL.1.2",
      "topic": "Reading and viewing",
      "lesson_variant": "step_by_step",
      "assessment_blueprint_id": "grade6-home-language-en-6-HL-1-2-recheck-v2",
      "activity_type": "remediation",
      "minutes": 20
    },
    {
      "misconception_tag": "procedure_without_conceptual_understanding",
      "caps_ref": "6.HL.1.2",
      "topic": "Reading and viewing",
      "lesson_variant": "step_by_step",
      "assessment_blueprint_id": "grade6-home-language-en-6-HL-1-2-recheck-v2",
      "activity_type": "remediation",
      "minutes": 20
    },
    {
      "misconception_tag": "topic_vocabulary_confusion",
      "caps_ref": "6.HL.1.3",
      "topic": "Writing and presenting",
      "lesson_variant": "step_by_step",
      "assessment_blueprint_id": "grade6-home-language-en-6-HL-1-3-recheck-v2",
      "activity_type": "remediation",
      "minutes": 20
    },
    {
      "misconception_tag": "procedure_without_conceptual_understanding",
      "caps_ref": "6.HL.1.3",
      "topic": "Writing and presenting",
      "lesson_variant": "step_by_step",
      "assessment_blueprint_id": "grade6-home-language-en-6-HL-1-3-recheck-v2",
      "activity_type": "remediation",
      "minutes": 20
    },
    {
      "misconception_tag": "topic_vocabulary_confusion",
      "caps_ref": "6.HL.1.4",
      "topic": "Language structures and conventions",
      "lesson_variant": "step_by_step",
      "assessment_blueprint_id": "grade6-home-language-en-6-HL-1-4-recheck-v2",
      "activity_type": "remediation",
      "minutes": 20
    },
    {
      "misconception_tag": "procedure_without_conceptual_understanding",
      "caps_ref": "6.HL.1.4",
      "topic": "Language structures and conventions",
      "lesson_variant": "step_by_step",
      "assessment_blueprint_id": "grade6-home-language-en-6-HL-1-4-recheck-v2",
      "activity_type": "remediation",
      "minutes": 20
    },
    {
      "misconception_tag": "topic_vocabulary_confusion",
      "caps_ref": "6.HL.2.1",
      "topic": "Listening and speaking",
      "lesson_variant": "step_by_step",
      "assessment_blueprint_id": "grade6-home-language-en-6-HL-2-1-recheck-v2",
      "activity_type": "remediation",
      "minutes": 20
    },
    {
      "misconception_tag": "procedure_without_conceptual_understanding",
      "caps_ref": "6.HL.2.1",
      "topic": "Listening and speaking",
      "lesson_variant": "step_by_step",
      "assessment_blueprint_id": "grade6-home-language-en-6-HL-2-1-recheck-v2",
      "activity_type": "remediation",
      "minutes": 20
    },
    {
      "misconception_tag": "topic_vocabulary_confusion",
      "caps_ref": "6.HL.2.2",
      "topic": "Reading and viewing",
      "lesson_variant": "step_by_step",
      "assessment_blueprint_id": "grade6-home-language-en-6-HL-2-2-recheck-v2",
      "activity_type": "remediation",
      "minutes": 20
    },
    {
      "misconception_tag": "procedure_without_conceptual_understanding",
      "caps_ref": "6.HL.2.2",
      "topic": "Reading and viewing",
      "lesson_variant": "step_by_step",
      "assessment_blueprint_id": "grade6-home-language-en-6-HL-2-2-recheck-v2",
      "activity_type": "remediation",
      "minutes": 20
    },
    {
      "misconception_tag": "topic_vocabulary_confusion",
      "caps_ref": "6.HL.2.3",
      "topic": "Writing and presenting",
      "lesson_variant": "step_by_step",
      "assessment_blueprint_id": "grade6-home-language-en-6-HL-2-3-recheck-v2",
      "activity_type": "remediation",
      "minutes": 20
    },
    {
      "misconception_tag": "procedure_without_conceptual_understanding",
      "caps_ref": "6.HL.2.3",
      "topic": "Writing and presenting",
      "lesson_variant": "step_by_step",
      "assessment_blueprint_id": "grade6-home-language-en-6-HL-2-3-recheck-v2",
      "activity_type": "remediation",
      "minutes": 20
    },
    {
      "misconception_tag": "topic_vocabulary_confusion",
      "caps_ref": "6.HL.2.4",
      "topic": "Language structures and conventions",
      "lesson_variant": "step_by_step",
      "assessment_blueprint_id": "grade6-home-language-en-6-HL-2-4-recheck-v2",
      "activity_type": "remediation",
      "minutes": 20
    },
    {
      "misconception_tag": "procedure_without_conceptual_understanding",
      "caps_ref": "6.HL.2.4",
      "topic": "Language structures and conventions",
      "lesson_variant": "step_by_step",
      "assessment_blueprint_id": "grade6-home-language-en-6-HL-2-4-recheck-v2",
      "activity_type": "remediation",
      "minutes": 20
    },
    {
      "misconception_tag": "topic_vocabulary_confusion",
      "caps_ref": "6.HL.3.1",
      "topic": "Listening and speaking",
      "lesson_variant": "step_by_step",
      "assessment_blueprint_id": "grade6-home-language-en-6-HL-3-1-recheck-v2",
      "activity_type": "remediation",
      "minutes": 20
    },
    {
      "misconception_tag": "procedure_without_conceptual_understanding",
      "caps_ref": "6.HL.3.1",
      "topic": "Listening and speaking",
      "lesson_variant": "step_by_step",
      "assessment_blueprint_id": "grade6-home-language-en-6-HL-3-1-recheck-v2",
      "activity_type": "remediation",
      "minutes": 20
    },
    {
      "misconception_tag": "topic_vocabulary_confusion",
      "caps_ref": "6.HL.3.2",
      "topic": "Reading and viewing",
      "lesson_variant": "step_by_step",
      "assessment_blueprint_id": "grade6-home-language-en-6-HL-3-2-recheck-v2",
      "activity_type": "remediation",
      "minutes": 20
    },
    {
      "misconception_tag": "procedure_without_conceptual_understanding",
      "caps_ref": "6.HL.3.2",
      "topic": "Reading and viewing",
      "lesson_variant": "step_by_step",
      "assessment_blueprint_id": "grade6-home-language-en-6-HL-3-2-recheck-v2",
      "activity_type": "remediation",
      "minutes": 20
    },
    {
      "misconception_tag": "topic_vocabulary_confusion",
      "caps_ref": "6.HL.3.3",
      "topic": "Writing and presenting",
      "lesson_variant": "step_by_step",
      "assessment_blueprint_id": "grade6-home-language-en-6-HL-3-3-recheck-v2",
      "activity_type": "remediation",
      "minutes": 20
    },
    {
      "misconception_tag": "procedure_without_conceptual_understanding",
      "caps_ref": "6.HL.3.3",
      "topic": "Writing and presenting",
      "lesson_variant": "step_by_step",
      "assessment_blueprint_id": "grade6-home-language-en-6-HL-3-3-recheck-v2",
      "activity_type": "remediation",
      "minutes": 20
    },
    {
      "misconception_tag": "topic_vocabulary_confusion",
      "caps_ref": "6.HL.3.4",
      "topic": "Language structures and conventions",
      "lesson_variant": "step_by_step",
      "assessment_blueprint_id": "grade6-home-language-en-6-HL-3-4-recheck-v2",
      "activity_type": "remediation",
      "minutes": 20
    },
    {
      "misconception_tag": "procedure_without_conceptual_understanding",
      "caps_ref": "6.HL.3.4",
      "topic": "Language structures and conventions",
      "lesson_variant": "step_by_step",
      "assessment_blueprint_id": "grade6-home-language-en-6-HL-3-4-recheck-v2",
      "activity_type": "remediation",
      "minutes": 20
    },
    {
      "misconception_tag": "topic_vocabulary_confusion",
      "caps_ref": "6.HL.4.1",
      "topic": "Listening and speaking",
      "lesson_variant": "step_by_step",
      "assessment_blueprint_id": "grade6-home-language-en-6-HL-4-1-recheck-v2",
      "activity_type": "remediation",
      "minutes": 20
    },
    {
      "misconception_tag": "procedure_without_conceptual_understanding",
      "caps_ref": "6.HL.4.1",
      "topic": "Listening and speaking",
      "lesson_variant": "step_by_step",
      "assessment_blueprint_id": "grade6-home-language-en-6-HL-4-1-recheck-v2",
      "activity_type": "remediation",
      "minutes": 20
    },
    {
      "misconception_tag": "topic_vocabulary_confusion",
      "caps_ref": "6.HL.4.2",
      "topic": "Reading and viewing",
      "lesson_variant": "step_by_step",
      "assessment_blueprint_id": "grade6-home-language-en-6-HL-4-2-recheck-v2",
      "activity_type": "remediation",
      "minutes": 20
    },
    {
      "misconception_tag": "procedure_without_conceptual_understanding",
      "caps_ref": "6.HL.4.2",
      "topic": "Reading and viewing",
      "lesson_variant": "step_by_step",
      "assessment_blueprint_id": "grade6-home-language-en-6-HL-4-2-recheck-v2",
      "activity_type": "remediation",
      "minutes": 20
    },
    {
      "misconception_tag": "topic_vocabulary_confusion",
      "caps_ref": "6.HL.4.3",
      "topic": "Writing and presenting",
      "lesson_variant": "step_by_step",
      "assessment_blueprint_id": "grade6-home-language-en-6-HL-4-3-recheck-v2",
      "activity_type": "remediation",
      "minutes": 20
    },
    {
      "misconception_tag": "procedure_without_conceptual_understanding",
      "caps_ref": "6.HL.4.3",
      "topic": "Writing and presenting",
      "lesson_variant": "step_by_step",
      "assessment_blueprint_id": "grade6-home-language-en-6-HL-4-3-recheck-v2",
      "activity_type": "remediation",
      "minutes": 20
    },
    {
      "misconception_tag": "topic_vocabulary_confusion",
      "caps_ref": "6.HL.4.4",
      "topic": "Language structures and conventions",
      "lesson_variant": "step_by_step",
      "assessment_blueprint_id": "grade6-home-language-en-6-HL-4-4-recheck-v2",
      "activity_type": "remediation",
      "minutes": 20
    },
    {
      "misconception_tag": "procedure_without_conceptual_understanding",
      "caps_ref": "6.HL.4.4",
      "topic": "Language structures and conventions",
      "lesson_variant": "step_by_step",
      "assessment_blueprint_id": "grade6-home-language-en-6-HL-4-4-recheck-v2",
      "activity_type": "remediation",
      "minutes": 20
    }
  ],
  "extension_mappings": [
    {
      "caps_ref": "6.HL.1.1",
      "topic": "Listening and speaking",
      "lesson_variant": "exam_style",
      "activity_type": "challenge",
      "assessment_blueprint_id": "grade6-home-language-en-6-HL-1-1-mastery-check-v2",
      "minutes": 25
    },
    {
      "caps_ref": "6.HL.1.2",
      "topic": "Reading and viewing",
      "lesson_variant": "exam_style",
      "activity_type": "challenge",
      "assessment_blueprint_id": "grade6-home-language-en-6-HL-1-2-mastery-check-v2",
      "minutes": 25
    },
    {
      "caps_ref": "6.HL.1.3",
      "topic": "Writing and presenting",
      "lesson_variant": "exam_style",
      "activity_type": "challenge",
      "assessment_blueprint_id": "grade6-home-language-en-6-HL-1-3-mastery-check-v2",
      "minutes": 25
    },
    {
      "caps_ref": "6.HL.1.4",
      "topic": "Language structures and conventions",
      "lesson_variant": "exam_style",
      "activity_type": "challenge",
      "assessment_blueprint_id": "grade6-home-language-en-6-HL-1-4-mastery-check-v2",
      "minutes": 25
    },
    {
      "caps_ref": "6.HL.2.1",
      "topic": "Listening and speaking",
      "lesson_variant": "exam_style",
      "activity_type": "challenge",
      "assessment_blueprint_id": "grade6-home-language-en-6-HL-2-1-mastery-check-v2",
      "minutes": 25
    },
    {
      "caps_ref": "6.HL.2.2",
      "topic": "Reading and viewing",
      "lesson_variant": "exam_style",
      "activity_type": "challenge",
      "assessment_blueprint_id": "grade6-home-language-en-6-HL-2-2-mastery-check-v2",
      "minutes": 25
    },
    {
      "caps_ref": "6.HL.2.3",
      "topic": "Writing and presenting",
      "lesson_variant": "exam_style",
      "activity_type": "challenge",
      "assessment_blueprint_id": "grade6-home-language-en-6-HL-2-3-mastery-check-v2",
      "minutes": 25
    },
    {
      "caps_ref": "6.HL.2.4",
      "topic": "Language structures and conventions",
      "lesson_variant": "exam_style",
      "activity_type": "challenge",
      "assessment_blueprint_id": "grade6-home-language-en-6-HL-2-4-mastery-check-v2",
      "minutes": 25
    },
    {
      "caps_ref": "6.HL.3.1",
      "topic": "Listening and speaking",
      "lesson_variant": "exam_style",
      "activity_type": "challenge",
      "assessment_blueprint_id": "grade6-home-language-en-6-HL-3-1-mastery-check-v2",
      "minutes": 25
    },
    {
      "caps_ref": "6.HL.3.2",
      "topic": "Reading and viewing",
      "lesson_variant": "exam_style",
      "activity_type": "challenge",
      "assessment_blueprint_id": "grade6-home-language-en-6-HL-3-2-mastery-check-v2",
      "minutes": 25
    },
    {
      "caps_ref": "6.HL.3.3",
      "topic": "Writing and presenting",
      "lesson_variant": "exam_style",
      "activity_type": "challenge",
      "assessment_blueprint_id": "grade6-home-language-en-6-HL-3-3-mastery-check-v2",
      "minutes": 25
    },
    {
      "caps_ref": "6.HL.3.4",
      "topic": "Language structures and conventions",
      "lesson_variant": "exam_style",
      "activity_type": "challenge",
      "assessment_blueprint_id": "grade6-home-language-en-6-HL-3-4-mastery-check-v2",
      "minutes": 25
    },
    {
      "caps_ref": "6.HL.4.1",
      "topic": "Listening and speaking",
      "lesson_variant": "exam_style",
      "activity_type": "challenge",
      "assessment_blueprint_id": "grade6-home-language-en-6-HL-4-1-mastery-check-v2",
      "minutes": 25
    },
    {
      "caps_ref": "6.HL.4.2",
      "topic": "Reading and viewing",
      "lesson_variant": "exam_style",
      "activity_type": "challenge",
      "assessment_blueprint_id": "grade6-home-language-en-6-HL-4-2-mastery-check-v2",
      "minutes": 25
    },
    {
      "caps_ref": "6.HL.4.3",
      "topic": "Writing and presenting",
      "lesson_variant": "exam_style",
      "activity_type": "challenge",
      "assessment_blueprint_id": "grade6-home-language-en-6-HL-4-3-mastery-check-v2",
      "minutes": 25
    },
    {
      "caps_ref": "6.HL.4.4",
      "topic": "Language structures and conventions",
      "lesson_variant": "exam_style",
      "activity_type": "challenge",
      "assessment_blueprint_id": "grade6-home-language-en-6-HL-4-4-mastery-check-v2",
      "minutes": 25
    }
  ],
  "pacing_guidance": {
    "lesson_block_minutes": 25,
    "practice_block_minutes": 15,
    "review_day": "Fri",
    "notes": "Alternate lesson and practice days. Use recheck blueprints after practice when misconception tags were missed."
  }
}
